{
  "version": "7",
  "dialect": "postgresql",
  "entries": [
    {
      "idx": 0,
      "version": "7",
      "when": 1756250001283,
      "tag": "0000_ancient_albert_cleary",
      "breakpoints": true
    },
    {
      "idx": 1,
      "version": "7",
      "when": 1773426308514,
      "tag": "0001_greedy_morbius",
      "breakpoints": true
    },
    {
      "idx": 2,
      "version": "7",
      "when": 1773689079808,
      "tag": "0002_premium_weapon_omega",
      "breakpoints": true
    },
    {
      "idx": 3,
      "version": "7",
      "when": 1773775651095,
      "tag": "0003_real_lionheart",
      "breakpoints": true
    },
    {
      "idx": 4,
      "version": "7",
      "when": 1773775707147,
      "tag": "0004_orange_ben_parker",
      "breakpoints": true
    }
  ]
}